runeatest/__init__.py
runeatest/nunitresults.py
runeatest/pysparkconnect.py
runeatest/testreporter.py
runeatest/utils.py
tests/__init__.py
tests/test_nunitresults.py
tests/test_testreporter.py
tests/test_utils.py
runeatest-0.27.33.dist-info/LICENSE
runeatest-0.27.33.dist-info/METADATA
runeatest-0.27.33.dist-info/WHEEL
runeatest-0.27.33.dist-info/top_level.txt
runeatest-0.27.33.dist-info/RECORD
